sealion/DimensionalityReduction.py
sealion/__init__.py
sealion/cython_decision_tree_functions.pyx
sealion/cython_ensemble_learning.pyx
sealion/cython_knn.pyx
sealion/cython_mixtures.pyx
sealion/cython_naive_bayes.pyx
sealion/cython_tsne.pyx
sealion/cython_unsupervised_clustering.pyx
sealion/decision_trees.py
sealion/ensemble_learning.py
sealion/mixtures.py
sealion/naive_bayes.py
sealion/nearest_neighbors.py
sealion/regression.py
sealion/setup.py
sealion/unsupervised_clustering.py
sealion/utils.py
sealion/neural_networks/__init__.py
sealion/neural_networks/_utils_nn.py
sealion/neural_networks/layers.py
sealion/neural_networks/loss.py
sealion/neural_networks/models.py
sealion/neural_networks/optimizers.py
sealion-4.4.5.dist-info/LICENSE
sealion-4.4.5.dist-info/METADATA
sealion-4.4.5.dist-info/WHEEL
sealion-4.4.5.dist-info/top_level.txt
sealion-4.4.5.dist-info/RECORD
