Metadata-Version: 2.1
Name: sealion
Version: 4.4.5
Summary: SeaLion is a comprehensive machine learning and data science library for beginners and ml-engineers alike.
Home-page: https://github.com/anish-lakkapragada/SeaLion
Author: Anish Lakkapragada
Author-email: anish.lakkapragada@gmail.com
License: Apache
Project-URL: Source Code, https://github.com/anish-lakkapragada/SeaLion
Keywords: Machine Learning,Data Science,Python
Platform: UNKNOWN
Classifier: Development Status :: 5 - Production/Stable
Classifier: Programming Language :: Python :: 3
Classifier: Programming Language :: Python :: 3.6
Classifier: Programming Language :: Python :: 3.7
Classifier: Programming Language :: Python :: 3.8
Classifier: Programming Language :: Python :: 3.9
Classifier: Intended Audience :: Developers
Classifier: Topic :: Software Development :: Build Tools
Classifier: License :: OSI Approved :: Apache Software License
Classifier: Programming Language :: Python :: 3
Requires-Python: >=3
License-File: LICENSE
Requires-Dist: numpy
Requires-Dist: joblib
Requires-Dist: pandas
Requires-Dist: scipy
Requires-Dist: tqdm
Requires-Dist: multiprocess
Requires-Dist: seaborn
Requires-Dist: Cython
Requires-Dist: setuptools
Requires-Dist: matplotlib
Requires-Dist: dill
Requires-Dist: pytz
Requires-Dist: cycler
Requires-Dist: pillow
Requires-Dist: kiwisolver
Requires-Dist: pyparsing
Requires-Dist: six
